pycodedoc/__init__.py
pycodedoc/cli.py
pycodedoc/costs.py
pycodedoc/docgen.py
pycodedoc/llm.py
pycodedoc/parser.py
pycodedoc/prompts.py
pycodedoc/utils.py
pycodedoc-0.1.0.dist-info/LICENSE
pycodedoc-0.1.0.dist-info/METADATA
pycodedoc-0.1.0.dist-info/WHEEL
pycodedoc-0.1.0.dist-info/entry_points.txt
pycodedoc-0.1.0.dist-info/top_level.txt
pycodedoc-0.1.0.dist-info/RECORD
