Metadata-Version: 2.1
Name: pycodedoc
Version: 0.1.0
Summary: Improve your codebase with LLMs using the right context for the right prompts.
Author-email: Manuel Renner <manuel.renner@diverger.ai>
License: MIT License
Project-URL: Source, https://github.com/DivergerThinking/pycodedoc
Project-URL: Homepage, https://diverger.ai
Requires-Python: <3.12,>=3.9
License-File: LICENSE
Requires-Dist: openai >=1.0
Requires-Dist: pydantic >=2.0
Requires-Dist: code2flow ==2.5.1
Requires-Dist: rich >=13.0
Requires-Dist: tenacity >=8.0
Requires-Dist: tiktoken
Requires-Dist: typer
Requires-Dist: toml
